MANIFEST.in
README.md
README.rst
setup.py
django_tool.egg-info/PKG-INFO
django_tool.egg-info/SOURCES.txt
django_tool.egg-info/dependency_links.txt
django_tool.egg-info/top_level.txt
djtool/__init__.py
djtool/apps.py
djtool/common.py
djtool/decorators.py
djtool/generics.py
djtool/mns.py
djtool/models.py
djtool/msgcode.py
djtool/oauth.py
djtool/review.py
djtool/views.py
djtool/dss/Mixin.py
djtool/dss/Serializer.py
djtool/dss/TimeFormatFactory.py
djtool/dss/Warning.py
djtool/dss/__init__.py